README.md
setup.py
data_retention/__init__.py
data_retention/admin.py
data_retention/apps.py
data_retention/models.py
data_retention/preferences.py
data_retention/tests.py
data_retention/views.py
data_retention.egg-info/PKG-INFO
data_retention.egg-info/SOURCES.txt
data_retention.egg-info/dependency_links.txt
data_retention.egg-info/top_level.txt
data_retention/migrations/__init__.py