Metadata-Version: 1.2
Name: data-retention
Version: 0.1.0
Summary: Papermerge App for data retention
Home-page: https://papermerge.com/
Author: Eugen Ciur
Author-email: eugen@papermerge.com
License: Apache 2.0 License
Platform: UNKNOWN
Classifier: Programming Language :: Python :: 3
Classifier: License :: OSI Approved :: Apache Software License
Classifier: Operating System :: OS Independent
Requires-Python: >=3.7
